setup.py
pipcolorlibraryV1/__init__.py
pipcolorlibraryV1.egg-info/PKG-INFO
pipcolorlibraryV1.egg-info/SOURCES.txt
pipcolorlibraryV1.egg-info/dependency_links.txt
pipcolorlibraryV1.egg-info/top_level.txt